{
  "630808": "https://www.surveymonkey.com/r/ZY6SF5Y",
  "685789": "https://www.surveymonkey.com/r/ZCTNDZB",
  "685790": "https://www.surveymonkey.com/r/ZQ2HGYB",
  "685793": "https://www.surveymonkey.com/r/5QLYVSP",
  "685792": "https://www.surveymonkey.com/r/ZWD32YW",
  "686997": "https://www.surveymonkey.com/r/5QPG3FY",
  "685794": "https://www.surveymonkey.com/r/ZSCTSCY",
  "685791": "https://www.surveymonkey.com/r/ZQGZRKK",
  "686957": "https://www.surveymonkey.com/r/ZFDQKZF",
  "686956": "https://www.surveymonkey.com/r/ZRDS7ZT",
  "686958": "https://www.surveymonkey.com/r/ZBQJ9VR",
  "686959": "https://www.surveymonkey.com/r/ZP3HP3M",
  "686962": "https://www.surveymonkey.com/r/Z6HHTKB",
  "686960": "https://www.surveymonkey.com/r/Z67C67P",
  "686961": "https://www.surveymonkey.com/r/Z6RMVBK",
  "686964": "https://www.surveymonkey.com/r/ZZ36FPS",
  "686963": "https://www.surveymonkey.com/r/ZZJJRBT",
  "713440": "https://www.surveymonkey.com/r/Z5LR8M8",
  "715879": "https://www.surveymonkey.com/r/YYDFXZC",
  "715885": "https://www.surveymonkey.com/r/Z6RMVBK",
  "686982": "https://www.surveymonkey.com/r/57VDY37",
  "686987": "https://www.surveymonkey.com/r/59RN5V9",
  "686986": "https://www.surveymonkey.com/r/59LJMRZ",
  "686980": "https://www.surveymonkey.com/r/5VFP3RY",
  "686979": "https://www.surveymonkey.com/r/5KM532T",
  "686984": "https://www.surveymonkey.com/r/57W5LNV",
  "689615": "https://www.surveymonkey.com/r/59ZNQDN",
  "713444": "https://www.surveymonkey.com/r/5DFYCFC",
  "686988": "https://www.surveymonkey.com/r/5DWLLQN",
  "715880": "https://www.surveymonkey.com/r/5Y8BRGY",
  "686993": "https://www.surveymonkey.com/r/523GQPG",
  "713516": "https://www.surveymonkey.com/r/5C5QZWK",
  "686989": "https://www.surveymonkey.com/r/5YXWHVG",
  "686994": "https://www.surveymonkey.com/r/5CDNR3Z",
  "686995": "https://www.surveymonkey.com/r/5CNK8ZH",
  "686991": "https://www.surveymonkey.com/r/522ZW5F",
  "687003": "https://www.surveymonkey.com/r/5QZHPNC",
  "686999": "https://www.surveymonkey.com/r/5JP97B6",
  "687002": "https://www.surveymonkey.com/r/5Q3788H",
  "687001": "https://www.surveymonkey.com/r/5QWB2TG",
  "687006": "https://www.surveymonkey.com/r/5W2G7BF",
  "687000": "https://www.surveymonkey.com/r/5QVHHGG",
  "687013": "https://www.surveymonkey.com/r/5TVHKH7",
  "687008": "https://www.surveymonkey.com/r/5S2J62N",
  "687007": "https://www.surveymonkey.com/r/5W68JLG",
  "687010": "https://www.surveymonkey.com/r/5RQDLJS",
  "687011": "https://www.surveymonkey.com/r/5RHRWZ3",
  "687014": "https://www.surveymonkey.com/r/5TS325R",
  "687015": "https://www.surveymonkey.com/r/DHXBFT9",
  "687016": "https://www.surveymonkey.com/r/DPZFHYZ",
  "687017": "https://www.surveymonkey.com/r/DPVFBQJ",
  "713446": "https://www.surveymonkey.com/r/2LG3659",
  "687019": "https://www.surveymonkey.com/r/D6GJ6F3",
  "687021": "https://www.surveymonkey.com/r/DZC8DLD",
  "687018": "https://www.surveymonkey.com/r/D6QNLGG",
  "687020": "https://www.surveymonkey.com/r/DZ8FSM7",
  "687023": "https://www.surveymonkey.com/r/DZMLKVR",
  "687024": "https://www.surveymonkey.com/r/D58BXG2",
  "687028": "https://www.surveymonkey.com/r/YKGT6KG",
  "687030": "https://www.surveymonkey.com/r/Y8QZDYZ",
  "687029": "https://www.surveymonkey.com/r/Y8LNH87",
  "687031": "https://www.surveymonkey.com/r/Y83QYJG",
  "687027": "https://www.surveymonkey.com/r/YKJDCBP",
  "687025": "https://www.surveymonkey.com/r/YKKBSCF",
  "717902": "https://www.surveymonkey.com/r/ZWBDVQF"
}
